cryptocodemanipal/RSA.py
cryptocodemanipal/__init__.py
cryptocodemanipal/diffie.py
cryptocodemanipal/ecc.py
cryptocodemanipal/elgamal.py
cryptocodemanipal/jacobi.py
cryptocodemanipal/miller.py
cryptocodemanipal/point.py
cryptocodemanipal/rabin.py
cryptocodemanipal/rsanolib.py
cryptocodemanipal/solvay.py
cryptocodemanipal-0.2.1.dist-info/licenses/LICENSE
cryptocodemanipal-0.2.1.dist-info/METADATA
cryptocodemanipal-0.2.1.dist-info/WHEEL
cryptocodemanipal-0.2.1.dist-info/top_level.txt
cryptocodemanipal-0.2.1.dist-info/RECORD
